[
  {
    "id": 20003014479,
    "node_id": "LE_lADOCqswNs7OuQBAzwAAAASoRcdP",
    "url": "https://api.github.com/repos/starship/starship/issues/events/20003014479",
    "actor": {
      "login": "Jisu-Woniu",
      "id": 31986081,
      "node_id": "MDQ6VXNlcjMxOTg2MDgx",
      "avatar_url": "https://avatars.githubusercontent.com/u/31986081?v=4",
      "gravatar_id": "",
      "url": "https://api.github.com/users/Jisu-Woniu",
      "html_url": "https://github.com/Jisu-Woniu",
      "followers_url": "https://api.github.com/users/Jisu-Woniu/followers",
      "following_url": "https://api.github.com/users/Jisu-Woniu/following{/other_user}",
      "gists_url": "https://api.github.com/users/Jisu-Woniu/gists{/gist_id}",
      "starred_url": "https://api.github.com/users/Jisu-Woniu/starred{/owner}{/repo}",
      "subscriptions_url": "https://api.github.com/users/Jisu-Woniu/subscriptions",
      "organizations_url": "https://api.github.com/users/Jisu-Woniu/orgs",
      "repos_url": "https://api.github.com/users/Jisu-Woniu/repos",
      "events_url": "https://api.github.com/users/Jisu-Woniu/events{/privacy}",
      "received_events_url": "https://api.github.com/users/Jisu-Woniu/received_events",
      "type": "User",
      "user_view_type": "public",
      "site_admin": false
    },
    "event": "labeled",
    "commit_id": null,
    "commit_url": null,
    "created_at": "2025-09-30T08:45:16Z",
    "label": {
      "name": "✨ enhancement",
      "color": "5EBEFF"
    },
    "performed_via_github_app": null
  },
  {
    "id": 20007352078,
    "node_id": "LE_lADOCqswNs7OuQBAzwAAAASoh_cO",
    "url": "https://api.github.com/repos/starship/starship/issues/events/20007352078",
    "actor": {
      "login": "davidkna",
      "id": 835177,
      "node_id": "MDQ6VXNlcjgzNTE3Nw==",
      "avatar_url": "https://avatars.githubusercontent.com/u/835177?v=4",
      "gravatar_id": "",
      "url": "https://api.github.com/users/davidkna",
      "html_url": "https://github.com/davidkna",
      "followers_url": "https://api.github.com/users/davidkna/followers",
      "following_url": "https://api.github.com/users/davidkna/following{/other_user}",
      "gists_url": "https://api.github.com/users/davidkna/gists{/gist_id}",
      "starred_url": "https://api.github.com/users/davidkna/starred{/owner}{/repo}",
      "subscriptions_url": "https://api.github.com/users/davidkna/subscriptions",
      "organizations_url": "https://api.github.com/users/davidkna/orgs",
      "repos_url": "https://api.github.com/users/davidkna/repos",
      "events_url": "https://api.github.com/users/davidkna/events{/privacy}",
      "received_events_url": "https://api.github.com/users/davidkna/received_events",
      "type": "User",
      "user_view_type": "public",
      "site_admin": false
    },
    "event": "labeled",
    "commit_id": null,
    "commit_url": null,
    "created_at": "2025-09-30T11:36:16Z",
    "label": {
      "name": "🌱 good first issue",
      "color": "ffa0e1"
    },
    "performed_via_github_app": null
  },
  {
    "id": 20101747108,
    "node_id": "REFE_lADOCqswNs7OuQBAzwAAAASuKFGk",
    "url": "https://api.github.com/repos/starship/starship/issues/events/20101747108",
    "actor": {
      "login": "Golenspade",
      "id": 154531132,
      "node_id": "U_kgDOCTX1PA",
      "avatar_url": "https://avatars.githubusercontent.com/u/154531132?v=4",
      "gravatar_id": "",
      "url": "https://api.github.com/users/Golenspade",
      "html_url": "https://github.com/Golenspade",
      "followers_url": "https://api.github.com/users/Golenspade/followers",
      "following_url": "https://api.github.com/users/Golenspade/following{/other_user}",
      "gists_url": "https://api.github.com/users/Golenspade/gists{/gist_id}",
      "starred_url": "https://api.github.com/users/Golenspade/starred{/owner}{/repo}",
      "subscriptions_url": "https://api.github.com/users/Golenspade/subscriptions",
      "organizations_url": "https://api.github.com/users/Golenspade/orgs",
      "repos_url": "https://api.github.com/users/Golenspade/repos",
      "events_url": "https://api.github.com/users/Golenspade/events{/privacy}",
      "received_events_url": "https://api.github.com/users/Golenspade/received_events",
      "type": "User",
      "user_view_type": "public",
      "site_admin": false
    },
    "event": "referenced",
    "commit_id": "31f9c01620093ff29b2a870697a1b7b641121782",
    "commit_url": "https://api.github.com/repos/Golenspade/starship/commits/31f9c01620093ff29b2a870697a1b7b641121782",
    "created_at": "2025-10-05T14:17:11Z",
    "performed_via_github_app": null
  },
  {
    "id": 20411601984,
    "node_id": "CE_lADOCqswNs7OuQBAzwAAAATAoFRA",
    "url": "https://api.github.com/repos/starship/starship/issues/events/20411601984",
    "actor": {
      "login": "davidkna",
      "id": 835177,
      "node_id": "MDQ6VXNlcjgzNTE3Nw==",
      "avatar_url": "https://avatars.githubusercontent.com/u/835177?v=4",
      "gravatar_id": "",
      "url": "https://api.github.com/users/davidkna",
      "html_url": "https://github.com/davidkna",
      "followers_url": "https://api.github.com/users/davidkna/followers",
      "following_url": "https://api.github.com/users/davidkna/following{/other_user}",
      "gists_url": "https://api.github.com/users/davidkna/gists{/gist_id}",
      "starred_url": "https://api.github.com/users/davidkna/starred{/owner}{/repo}",
      "subscriptions_url": "https://api.github.com/users/davidkna/subscriptions",
      "organizations_url": "https://api.github.com/users/davidkna/orgs",
      "repos_url": "https://api.github.com/users/davidkna/repos",
      "events_url": "https://api.github.com/users/davidkna/events{/privacy}",
      "received_events_url": "https://api.github.com/users/davidkna/received_events",
      "type": "User",
      "user_view_type": "public",
      "site_admin": false
    },
    "event": "closed",
    "commit_id": null,
    "commit_url": null,
    "created_at": "2025-10-21T18:03:17Z",
    "state_reason": null,
    "performed_via_github_app": null
  }
]