[
  {
    "url": "https://api.github.com/repos/starship/starship/issues/comments/2046569055",
    "html_url": "https://github.com/starship/starship/issues/5916#issuecomment-2046569055",
    "issue_url": "https://api.github.com/repos/starship/starship/issues/5916",
    "id": 2046569055,
    "node_id": "IC_kwDOCqswNs55_Cpf",
    "user": {
      "login": "UniqueDing",
      "id": 24190814,
      "node_id": "MDQ6VXNlcjI0MTkwODE0",
      "avatar_url": "https://avatars.githubusercontent.com/u/24190814?v=4",
      "gravatar_id": "",
      "url": "https://api.github.com/users/UniqueDing",
      "html_url": "https://github.com/UniqueDing",
      "followers_url": "https://api.github.com/users/UniqueDing/followers",
      "following_url": "https://api.github.com/users/UniqueDing/following{/other_user}",
      "gists_url": "https://api.github.com/users/UniqueDing/gists{/gist_id}",
      "starred_url": "https://api.github.com/users/UniqueDing/starred{/owner}{/repo}",
      "subscriptions_url": "https://api.github.com/users/UniqueDing/subscriptions",
      "organizations_url": "https://api.github.com/users/UniqueDing/orgs",
      "repos_url": "https://api.github.com/users/UniqueDing/repos",
      "events_url": "https://api.github.com/users/UniqueDing/events{/privacy}",
      "received_events_url": "https://api.github.com/users/UniqueDing/received_events",
      "type": "User",
      "user_view_type": "public",
      "site_admin": false
    },
    "created_at": "2024-04-10T05:33:09Z",
    "updated_at": "2024-04-10T05:33:09Z",
    "body": "I have found the solution. It's set LOCALE_ARCHIVE=${glibcLocales}/lib/locale/locale-archive",
    "author_association": "NONE",
    "pin": null,
    "reactions": {
      "url": "https://api.github.com/repos/starship/starship/issues/comments/2046569055/reactions",
      "total_count": 0,
      "+1": 0,
      "-1": 0,
      "laugh": 0,
      "hooray": 0,
      "confused": 0,
      "heart": 0,
      "rocket": 0,
      "eyes": 0
    },
    "performed_via_github_app": null
  }
]